MANIFEST.in
README.md
setup.py
repo_sync.egg-info/PKG-INFO
repo_sync.egg-info/SOURCES.txt
repo_sync.egg-info/dependency_links.txt
repo_sync.egg-info/entry_points.txt
repo_sync.egg-info/requires.txt
repo_sync.egg-info/top_level.txt
reposync/cli.py