Metadata-Version: 1.1
Name: repo-sync
Version: 0.2.5
Summary: Sync remotes to other remotes.
Home-page: https://github.com/makefu/repo-sync
Author: makefu
Author-email: github@syntax-fehler.de
License: MIT
Keywords: repo sync
Platform: UNKNOWN
Classifier: Intended Audience :: Developers
Classifier: Topic :: Software Development :: Libraries :: Python Modules
Classifier: Programming Language :: Python :: 2
Classifier: Programming Language :: Python :: 3
